Metadata-Version: 2.1
Name: SpeechRecognition
Version: 3.10.4
Summary: Library for performing speech recognition, with support for several engines and APIs, online and offline.
Home-page: https://github.com/Uberi/speech_recognition#readme
Author: Anthony Zhang (Uberi)
Author-email: azhang9@gmail.com
License: BSD
Keywords: speech recognition voice sphinx google wit bing api houndify ibm snowboy
Classifier: Development Status :: 5 - Production/Stable
Classifier: Intended Audience :: Developers
Classifier: Natural Language :: English
Classifier: License :: OSI Approved :: BSD License
Classifier: Operating System :: Microsoft :: Windows
Classifier: Operating System :: POSIX :: Linux
Classifier: Operating System :: MacOS :: MacOS X
Classifier: Operating System :: Other OS
Classifier: Programming Language :: Python
Classifier: Programming Language :: Python :: 3
Classifier: Programming Language :: Python :: 3.8
Classifier: Programming Language :: Python :: 3.9
Classifier: Programming Language :: Python :: 3.10
Classifier: Programming Language :: Python :: 3.11
Classifier: Topic :: Software Development :: Libraries :: Python Modules
Classifier: Topic :: Multimedia :: Sound/Audio :: Speech
Requires-Python: >=3.8
License-File: LICENSE-FLAC.txt
License-File: LICENSE.txt
Requires-Dist: requests>=2.26.0
Requires-Dist: typing-extensions
Provides-Extra: dev
Requires-Dist: flake8; extra == "dev"
Requires-Dist: rstcheck; extra == "dev"
Provides-Extra: whisper-local
Requires-Dist: openai-whisper; extra == "whisper-local"
Requires-Dist: soundfile; extra == "whisper-local"
Provides-Extra: whisper-api
Requires-Dist: openai; extra == "whisper-api"
